velotest/__init__.py
velotest/explicit_hypothesis_testing.py
velotest/hypothesis_testing.py
velotest/neighbors.py
velotest/plotting.py
velotest/step_function.py
velotest/test_statistic.py
velotest/test_statistic_function.py
velotest/util.py
velotest-0.0.1.dist-info/licenses/LICENSE
velotest-0.0.1.dist-info/METADATA
velotest-0.0.1.dist-info/WHEEL
velotest-0.0.1.dist-info/top_level.txt
velotest-0.0.1.dist-info/RECORD
