Metadata-Version: 2.4
Name: velotest
Version: 0.0.1
Summary: A hypothesis test for velocity embeddings.
Author-email: Sebastian Bischoff <sebastian.bischoff@uni-tuebingen.de>
License-Expression: MIT
Project-URL: Repository, https://github.com/mackelab/velocity-hypothesis-test/
Project-URL: Issues, https://github.com/mackelab/velocity-hypothesis-test/issues
Project-URL: Documentation, https://velocity-hypothesis-test.readthedocs.io/en/latest/index.html
Classifier: Programming Language :: Python :: 3
Classifier: Operating System :: OS Independent
Classifier: Topic :: Scientific/Engineering :: Bio-Informatics
Requires-Python: >=3.9
License-File: LICENSE
Requires-Dist: torch>=2.1.2
Requires-Dist: numpy>=1.26.4
Requires-Dist: scikit-learn>=1.3.0
Requires-Dist: tqdm>=4.66.1
Requires-Dist: matplotlib>=3.8.2
Requires-Dist: pandas>=2.1.4
Requires-Dist: scvelo>=0.3.2
Provides-Extra: experiment
Requires-Dist: hydra-core>=1.3.2; extra == "experiment"
Provides-Extra: docs
Requires-Dist: sphinx>=7.4.7; extra == "docs"
Provides-Extra: dev
Requires-Dist: pytest>=8.3.5; extra == "dev"
Requires-Dist: parameterized>=0.9.0; extra == "dev"
Dynamic: license-file
